mflog/__init__.py
mflog/log.py
mflog/processors.py
mflog/syslog.py
mflog/unittests.py
mflog/utils.py
mflog-0.1.1.dist-info/licenses/LICENSE
mflog-0.1.1.dist-info/METADATA
mflog-0.1.1.dist-info/WHEEL
mflog-0.1.1.dist-info/entry_points.txt
mflog-0.1.1.dist-info/top_level.txt
mflog-0.1.1.dist-info/RECORD
