Metadata-Version: 2.4
Name: mflog
Version: 0.1.1
Summary: opinionated python (structured) logging library built on structlog
Home-page: https://github.com/metwork-framework/mflog
Author: Fabien MARTY
Author-email: fabien.marty@gmail.com
License: BSD 3
Requires-Python: >=2.7
License-File: LICENSE
Requires-Dist: structlog>=19.1.0
Requires-Dist: six
Dynamic: author
Dynamic: author-email
Dynamic: description
Dynamic: description-content-type
Dynamic: home-page
Dynamic: license
Dynamic: license-file
Dynamic: requires-dist
Dynamic: requires-python
Dynamic: summary
